{"created": 1692879492, "asn": {"aut-num": ["AS4201270004"], "as-name": ["frank"], "admin-c": ["FRANK-NEONETWORK"], "tech-c": ["FRANK-NEONETWORK"], "remarks": ["Imported from neonetwork, do not edit!"], "mnt-by": ["DN42-MNT"], "source": ["NEONETWORK"], "contact-info": {"person": ["frank"], "nic-hdl": ["FRANK-NEONETWORK"], "remarks": ["Imported from neonetwork, do not edit!"], "mnt-by": ["DN42-MNT"], "source": ["NEONETWORK"]}}, "routes": {"ipv4": [{"route": ["10.127.56.0/24"], "max-length": ["29"], "origin": ["AS4201270004"], "admin-c": ["FRANK-NEONETWORK"], "tech-c": ["FRANK-NEONETWORK"], "remarks": ["Imported from neonetwork, do not edit!"], "mnt-by": ["DN42-MNT"], "source": ["NEONETWORK"], "inetnum": {"cidr": ["10.127.56.0/24"], "netname": ["frank-hsinchu"], "admin-c": ["FRANK-NEONETWORK"], "tech-c": ["FRANK-NEONETWORK"], "remarks": ["Imported from neonetwork, do not edit!"], "mnt-by": ["DN42-MNT"], "source": ["NEONETWORK"]}, "visible": false}, {"route": ["10.127.255.56/32"], "max-length": ["32"], "origin": ["AS4201270004"], "admin-c": ["FRANK-NEONETWORK"], "tech-c": ["FRANK-NEONETWORK"], "remarks": ["Imported from neonetwork, do not edit!"], "mnt-by": ["DN42-MNT"], "source": ["NEONETWORK"], "inetnum": {"cidr": ["10.127.255.56/32"], "netname": ["frank-hsinchu-1"], "admin-c": ["FRANK-NEONETWORK"], "tech-c": ["FRANK-NEONETWORK"], "remarks": ["Imported from neonetwork, do not edit!"], "mnt-by": ["DN42-MNT"], "source": ["NEONETWORK"]}, "visible": false}], "ipv6": []}}