{"created": 1688051769, "asn": {"aut-num": ["AS4242422678"], "as-name": ["SKUSAVI-AS"], "admin-c": ["SKUSAVI-DN42"], "tech-c": ["SKUSAVI-DN42"], "mnt-by": ["SKUSAVI-MNT"], "source": ["DN42"], "contact-info": {"person": ["Savi Savi"], "contact": ["sedoardo98@gmail.com"], "nic-hdl": ["SKUSAVI-DN42"], "mnt-by": ["SKUSAVI-MNT"], "source": ["DN42"], "pgp-fingerprint": "pgp-fingerprint 9D6ED14798AFFE9EB85B241BF97E1CA5194DDDF4"}}, "routes": {"ipv4": [{"route": ["172.23.151.144/28"], "origin": ["AS4242422678"], "mnt-by": ["SKUSAVI-MNT"], "source": ["DN42"], "inetnum": {"cidr": ["172.23.151.144/28"], "netname": ["SKUFOUR1-NETWORK"], "admin-c": ["SKUSAVI-DN42"], "tech-c": ["SKUSAVI-DN42"], "mnt-by": ["SKUSAVI-MNT"], "nserver": ["ns.skusavi.dn42"], "status": ["ASSIGNED"], "source": ["DN42"]}, "visible": false}], "ipv6": [{"route6": ["fd5f:b56c:2823::/48"], "origin": ["AS4242422678"], "mnt-by": ["SKUSAVI-MNT"], "source": ["DN42"], "inetnum": {"cidr": ["fd5f:b56c:2823::/48"], "netname": ["SKUSIX1-NETWORK"], "descr": ["First IPv6 network of Sku Savi"], "country": ["IT"], "admin-c": ["SKUSAVI-DN42"], "tech-c": ["SKUSAVI-DN42"], "mnt-by": ["SKUSAVI-MNT"], "nserver": ["ns.skusavi.dn42"], "status": ["ASSIGNED"], "source": ["DN42"]}, "visible": false}]}}