{"created": 1693305752, "asn": {"aut-num": ["AS4242423510"], "descr": ["Inftyloop.tech experimental AS"], "admin-c": ["INFTYLOOP-DN42"], "tech-c": ["INFTYLOOP-DN42"], "mnt-by": ["INFTYLOOP-MNT"], "as-name": ["INFTYLOOP-AS"], "source": ["DN42"], "contact-info": {"person": ["zx1239856"], "contact": ["zx1239856@gmail.com"], "nic-hdl": ["INFTYLOOP-DN42"], "mnt-by": ["INFTYLOOP-MNT"], "source": ["DN42"], "pgp-fingerprint": "pgp-fingerprint E9D53E36C446711110351A53CF8BF612FAF3C351"}}, "routes": {"ipv4": [{"route": ["172.23.178.0/26"], "origin": ["AS4242423510"], "mnt-by": ["INFTYLOOP-MNT"], "source": ["DN42"], "inetnum": {"netname": ["INFTYLOOP-NETWORK"], "descr": ["Network of inftyloop.tech"], "country": ["CN"], "admin-c": ["INFTYLOOP-DN42"], "tech-c": ["INFTYLOOP-DN42"], "mnt-by": ["INFTYLOOP-MNT"], "status": ["ASSIGNED"], "cidr": ["172.23.178.0/26"], "source": ["DN42"]}, "visible": false}], "ipv6": [{"route6": ["fd69:3053:a295::/48"], "origin": ["AS4242423510"], "mnt-by": ["INFTYLOOP-MNT"], "source": ["DN42"], "inetnum": {"cidr": ["fd69:3053:a295::/48"], "netname": ["INFTYLOOP-NETWORK"], "descr": ["Network of inftyloop.tech"], "country": ["CN"], "admin-c": ["INFTYLOOP-DN42"], "tech-c": ["INFTYLOOP-DN42"], "mnt-by": ["INFTYLOOP-MNT"], "status": ["ASSIGNED"], "source": ["DN42"]}, "visible": false}]}}