{"created": 1695901129, "asn": {"aut-num": ["AS4242422711"], "as-name": ["AS-MAYA-DS42"], "admin-c": ["MAYA-DN42"], "tech-c": ["MAYA-DN42"], "mnt-by": ["MAYA-MNT"], "source": ["DN42"], "contact-info": {"person": ["Maya"], "e-mail": ["naval@europe.com"], "nic-hdl": ["MAYA-DN42"], "mnt-by": ["MAYA-MNT"], "source": ["DN42"], "pgp-fingerprint": "pgp-fingerprint ECFB86EECB1236448A06970AAABAB510F1BC251C"}}, "routes": {"ipv4": [], "ipv6": [{"route6": ["fd3b:d3a:3d6::/48"], "origin": ["AS4242422711"], "max-length": ["48"], "mnt-by": ["MAYA-MNT"], "source": ["DN42"], "inetnum": {"cidr": ["fd3b:d3a:3d6::/48"], "netname": ["MAYA-RED"], "descr": ["Red Maya"], "country": ["ES"], "admin-c": ["MAYA-DN42"], "tech-c": ["MAYA-DN42"], "mnt-by": ["MAYA-MNT"], "status": ["ASSIGNED"], "source": ["DN42"], "nserver": ["ns1.maya.dn42", "ns2.maya.dn42"]}, "visible": false}]}}