{"created": 1690463814, "asn": {"aut-num": ["AS4242420565"], "as-name": ["E1MO-AS"], "admin-c": ["E1MO-DN42"], "tech-c": ["E1MO-DN42"], "mnt-by": ["E1MO-MNT"], "source": ["DN42"], "contact-info": {"person": ["e1mo"], "contact": ["dn42@e1mo.de", "matrix: @e1mo:chaos.jetzt"], "nic-hdl": ["E1MO-DN42"], "mnt-by": ["E1MO-MNT"], "source": ["DN42"], "pgp-fingerprint": "PGPKEY-A85BAADA"}}, "routes": {"ipv4": [{"route": ["172.20.229.160/27"], "origin": ["AS4242420565"], "max-length": ["29"], "mnt-by": ["E1MO-MNT"], "source": ["DN42"], "inetnum": {"cidr": ["172.20.229.160/27"], "netname": ["E1MO-NETWORK"], "admin-c": ["E1MO-DN42"], "tech-c": ["E1MO-DN42"], "mnt-by": ["E1MO-MNT"], "status": ["ASSIGNED"], "nserver": ["ns1.e1mo.dn42", "ns2.e1mo.dn42"], "source": ["DN42"]}, "visible": false}], "ipv6": [{"route6": ["fded:e0fd:5fe::/48"], "origin": ["AS4242420565"], "max-length": ["64"], "mnt-by": ["E1MO-MNT"], "source": ["DN42"], "inetnum": {"cidr": ["fded:e0fd:5fe::/48"], "netname": ["E1MO-NET-1"], "admin-c": ["E1MO-DN42"], "tech-c": ["E1MO-DN42"], "mnt-by": ["E1MO-MNT"], "status": ["ASSIGNED"], "nserver": ["ns1.e1mo.dn42", "ns2.e1mo.dn42"], "source": ["DN42"]}, "visible": false}]}}