{"created": 1733998607, "asn": {"aut-num": ["AS4242422370"], "as-name": ["MIXX-AS"], "admin-c": ["MIXX-DN42"], "tech-c": ["MIXX-DN42"], "mnt-by": ["MIXX-MNT"], "source": ["DN42"], "contact-info": {"person": ["Mixx"], "e-mail": ["mihail74sal@gmail.com"], "nic-hdl": ["MIXX-DN42"], "mnt-by": ["MIXX-MNT"], "source": ["DN42"], "pgp-fingerprint": "pgp-fingerprint 22B7400A9FD3A2654628F165BEE3C81AF81089AA"}}, "routes": {"ipv4": [{"route": ["172.23.180.224/27"], "origin": ["AS4242422370"], "max-length": ["27"], "mnt-by": ["MIXX-MNT"], "source": ["DN42"], "inetnum": {"cidr": ["172.23.180.224/27"], "netname": ["MIXX-NETWORK"], "descr": ["Network of Mixx"], "country": ["RU"], "admin-c": ["MIXX-DN42"], "tech-c": ["MIXX-DN42"], "mnt-by": ["MIXX-MNT"], "status": ["ASSIGNED"], "source": ["DN42"]}, "visible": false}], "ipv6": [{"route6": ["fd4e:83cb:acac::/48"], "origin": ["AS4242422370"], "max-length": ["48"], "mnt-by": ["MIXX-MNT"], "source": ["DN42"], "inetnum": {"cidr": ["fd4e:83cb:acac::/48"], "netname": ["MIXX-NETWORK"], "descr": ["Network of Mixx"], "country": ["RU"], "admin-c": ["MIXX-DN42"], "tech-c": ["MIXX-DN42"], "mnt-by": ["MIXX-MNT"], "status": ["ASSIGNED"], "source": ["DN42"]}, "visible": true}]}}