{"created": 1688401061, "asn": {"aut-num": ["AS4242423921"], "as-name": ["KUSTAV DN42 AS"], "admin-c": ["KUSTAV-DN42"], "tech-c": ["KUSTAV-DN42"], "mnt-by": ["KUS-MNT"], "source": ["DN42"], "contact-info": {"person": ["KUSTAV"], "contact": ["mail:kustav@live.com"], "nic-hdl": ["KUSTAV-DN42"], "mnt-by": ["KUS-MNT"], "source": ["DN42"]}}, "routes": {"ipv4": [{"route": ["172.23.230.0/26"], "origin": ["AS4242423921"], "mnt-by": ["KUS-MNT"], "source": ["DN42"], "inetnum": {"cidr": ["172.23.230.0/26"], "netname": ["KUSTAV DN42 POOL"], "admin-c": ["KUSTAV-DN42"], "tech-c": ["KUSTAV-DN42"], "mnt-by": ["KUS-MNT"], "status": ["ASSIGNED"], "source": ["DN42"]}, "visible": false}], "ipv6": []}}