{"created": 1688129998, "asn": {"aut-num": ["AS4242423169"], "as-name": ["CLEMENTPRIMOT-AS"], "admin-c": ["CLEMENTPRIMOT-DN42"], "tech-c": ["CLEMENTPRIMOT-DN42"], "mnt-by": ["CLEMENTPRIMOT-MNT"], "source": ["DN42"], "contact-info": {"person": ["Clement Primot"], "contact": ["clement.primot@protonmail.com", "twitter: voltingg", "irc:clementprimot@hackint"], "nic-hdl": ["CLEMENTPRIMOT-DN42"], "mnt-by": ["CLEMENTPRIMOT-MNT"], "source": ["DN42"], "pgp-fingerprint": "pgp-fingerprint 41B66C635BA4A0D956913A0D8D9C52FE493D3154"}}, "routes": {"ipv4": [{"route": ["172.20.164.128/26"], "origin": ["AS4242423169"], "mnt-by": ["CLEMENTPRIMOT-MNT"], "source": ["DN42"], "inetnum": {"cidr": ["172.20.164.128/26"], "netname": ["CLEMENTPRIMOT-NETWORK"], "admin-c": ["CLEMENTPRIMOT-DN42"], "tech-c": ["CLEMENTPRIMOT-DN42"], "mnt-by": ["CLEMENTPRIMOT-MNT"], "status": ["ASSIGNED"], "source": ["DN42"]}, "visible": false}], "ipv6": [{"route6": ["fd42:1ebc:34f0::/48"], "origin": ["AS4242423169"], "mnt-by": ["CLEMENTPRIMOT-MNT"], "source": ["DN42"], "inetnum": {"cidr": ["fd42:1ebc:34f0::/48"], "netname": ["CLEMENTPRIMOT-NETWORK"], "descr": ["Clement Primot Network"], "country": ["FR"], "admin-c": ["CLEMENTPRIMOT-DN42"], "tech-c": ["CLEMENTPRIMOT-DN42"], "mnt-by": ["CLEMENTPRIMOT-MNT"], "status": ["ASSIGNED"], "source": ["DN42"]}, "visible": false}]}}