{"created": 1695550319, "asn": {"aut-num": ["AS4242423755"], "as-name": ["LEBHERZ"], "descr": ["LEBHERZ-1"], "admin-c": ["LEBHERZ-DN42"], "tech-c": ["LEBHERZ-DN42"], "mnt-by": ["DE-LEBHERZ-MNT"], "source": ["DN42"], "contact-info": {"person": ["John Lebherz"], "contact": ["info@systemhaus-lebherz.de"], "nic-hdl": ["LEBHERZ-DN42"], "mnt-by": ["DE-LEBHERZ-MNT"], "source": ["DN42"]}}, "routes": {"ipv4": [], "ipv6": [{"route6": ["fda8:5557:beb7::/48"], "origin": ["AS4242423755"], "mnt-by": ["DE-LEBHERZ-MNT"], "source": ["DN42"], "inetnum": {"netname": ["LEBHERZ-V6-1"], "descr": ["LEBHERZ-IPv6-1"], "country": ["DE"], "admin-c": ["LEBHERZ-DN42"], "tech-c": ["LEBHERZ-DN42"], "mnt-by": ["DE-LEBHERZ-MNT"], "nserver": ["ns1.lebherz.dn42"], "status": ["ASSIGNED"], "cidr": ["fda8:5557:beb7::/48"], "source": ["DN42"]}, "visible": false}]}}