{"created": 1688224476, "asn": {"aut-num": ["AS4242421130"], "as-name": ["BONJOU2333-AS"], "descr": ["Peer with me at bonjou2333@gmail.com"], "admin-c": ["BONJOU2333-DN42"], "tech-c": ["BONJOU2333-DN42"], "mnt-by": ["BONJOU2333-MNT"], "source": ["DN42"], "contact-info": {"person": ["Bonjou2333"], "contact": ["bonjou2333@gmail.com"], "nic-hdl": ["BONJOU2333-DN42"], "mnt-by": ["BONJOU2333-MNT"], "source": ["DN42"], "pgp-fingerprint": "pgp-fingerprint BA301AFDC53780ECE36307F76D41C706AA8F2D18"}}, "routes": {"ipv4": [{"route": ["172.20.233.64/26"], "descr": ["Peer with me at bonjou2333@gmail.com"], "origin": ["AS4242421130"], "mnt-by": ["BONJOU2333-MNT"], "source": ["DN42"], "inetnum": {"netname": ["BONJOU2333-IPV4"], "remarks": ["Peer with me at bonjou2333@gmail.com"], "descr": ["Peer with me at bonjou2333@gmail.com"], "country": ["CN"], "admin-c": ["BONJOU2333-DN42"], "tech-c": ["BONJOU2333-DN42"], "mnt-by": ["BONJOU2333-MNT"], "status": ["ASSIGNED"], "cidr": ["172.20.233.64/26"], "source": ["DN42"]}, "visible": false}], "ipv6": [{"route6": ["fd42:1130::/48"], "descr": ["Peer with me at bonjou2333@gmail.com"], "origin": ["AS4242421130"], "mnt-by": ["BONJOU2333-MNT"], "source": ["DN42"], "inetnum": {"netname": ["BONJOU2333-IPV6"], "descr": ["Peer with me at bonjou2333@gmail.com"], "country": ["CN"], "admin-c": ["BONJOU2333-DN42"], "tech-c": ["BONJOU2333-DN42"], "mnt-by": ["BONJOU2333-MNT"], "status": ["ASSIGNED"], "cidr": ["fd42:1130::/48"], "source": ["DN42"]}, "visible": false}]}}