{"created": 1691770726, "asn": {"aut-num": ["AS4242422891"], "as-name": ["TIMWEB"], "descr": ["wp.TimWeb.ca over dn42"], "admin-c": ["TIMWEB-DN42"], "tech-c": ["TIMWEB-DN42"], "mnt-by": ["TIMWEB-MNT"], "source": ["DN42"], "contact-info": {"person": ["dummy person object"], "contact": ["mail:root@nic.dn42"], "nic-hdl": ["DUMMY-DN42"], "mnt-by": ["DUMMY-MNT"], "source": ["DN42"]}}, "routes": {"ipv4": [], "ipv6": [{"route6": ["fdbb:35ff:aa4e::/48"], "descr": ["TIMWEB"], "origin": ["AS4242422891"], "mnt-by": ["TIMWEB-MNT"], "source": ["DN42"], "inetnum": {"netname": ["TIMWEB-NETWORK"], "descr": ["Tim's Web"], "country": ["CA"], "admin-c": ["TIMWEB-DN42"], "tech-c": ["TIMWEB-DN42"], "mnt-by": ["TIMWEB-MNT"], "nserver": ["ns4.timweb.ca"], "status": ["ALLOCATED"], "cidr": ["fdbb:35ff:aa4e::/48"], "source": ["DN42"]}, "visible": false}]}}