{"created": 1691050495, "asn": {"aut-num": ["AS4242421604"], "as-name": ["LIBECHO-AS"], "descr": ["Tony's Main network, open to peering."], "admin-c": ["LIBECHO-DN42"], "tech-c": ["LIBECHO-DN42"], "mnt-by": ["LIBECHO-MNT"], "source": ["DN42"], "contact-info": {"person": ["Tony Libecho"], "e-mail": ["i@iamsjy.com"], "contact": ["github:hmsjy2017"], "nic-hdl": ["LIBECHO-DN42"], "mnt-by": ["LIBECHO-MNT"], "source": ["DN42"], "pgp-fingerprint": "pgp-fingerprint 6251718B12D5F6ED360EAC27D3ED9C7CFB9E0346"}}, "routes": {"ipv4": [{"route": ["172.22.111.96/28"], "descr": ["Tony's IP space"], "origin": ["AS4242421604"], "mnt-by": ["LIBECHO-MNT"], "source": ["DN42"], "inetnum": {"netname": ["LIBECHO-IPV4"], "descr": ["Tony's IP space"], "country": ["CN"], "admin-c": ["LIBECHO-DN42"], "tech-c": ["LIBECHO-DN42"], "mnt-by": ["LIBECHO-MNT"], "status": ["ASSIGNED"], "cidr": ["172.22.111.96/28"], "source": ["DN42"]}, "visible": false}], "ipv6": [{"route6": ["fd10:e0b:bb2::/48"], "descr": ["Tony's IP space"], "origin": ["AS4242421604", "AS4242421604"], "mnt-by": ["LIBECHO-MNT"], "source": ["DN42"], "inetnum": {"netname": ["LIBECHO-IPV6"], "descr": ["Tony's IP space"], "country": ["CN"], "admin-c": ["LIBECHO-DN42"], "tech-c": ["LIBECHO-DN42"], "mnt-by": ["LIBECHO-MNT"], "status": ["ASSIGNED"], "cidr": ["fd10:e0b:bb2::/48"], "source": ["DN42"]}, "visible": false}]}}