{"created": 1694468293, "asn": {"aut-num": ["AS4242423854"], "as-name": ["AS for MITORAJ Network"], "admin-c": ["MITORAJ-DN42"], "tech-c": ["MITORAJ-DN42"], "mnt-by": ["MITORAJ-MNT"], "source": ["DN42"], "contact-info": {"person": ["Jan Mitoraj"], "contact": ["jan@mitoraj.cz"], "nic-hdl": ["MITORAJ-DN42"], "mnt-by": ["MITORAJ-MNT"], "source": ["DN42"], "pgp-fingerprint": "PGPKEY-F3AE3B34"}}, "routes": {"ipv4": [{"route": ["172.20.33.96/27"], "origin": ["AS4242423854"], "mnt-by": ["MITORAJ-MNT"], "source": ["DN42"], "inetnum": {"cidr": ["172.20.33.96/27"], "netname": ["MITORAJ-NETWORK"], "admin-c": ["MITORAJ-DN42"], "tech-c": ["MITORAJ-DN42"], "mnt-by": ["MITORAJ-MNT"], "nserver": ["ns1.mitoraj.dn42", "ns2.mitoraj.dn42"], "status": ["ASSIGNED"], "source": ["DN42"]}, "visible": false}], "ipv6": [{"route6": ["fdc8:200e:654a::/48"], "origin": ["AS4242423854"], "mnt-by": ["MITORAJ-MNT"], "source": ["DN42"], "inetnum": {"cidr": ["fdc8:200e:654a::/48"], "netname": ["MITORAJ-NET-1"], "admin-c": ["MITORAJ-DN42"], "tech-c": ["MITORAJ-DN42"], "mnt-by": ["MITORAJ-MNT"], "nserver": ["ns1.mitoraj.dn42", "ns2.mitoraj.dn42"], "status": ["ASSIGNED"], "source": ["DN42"]}, "visible": false}]}}