{"created": 1734776059, "asn": {"aut-num": ["AS4242423424"], "as-name": ["AS-MAKURU-DN42"], "admin-c": ["MAKURU-DN42"], "tech-c": ["MAKURU-DN42"], "mnt-by": ["MAKURU-MNT"], "source": ["DN42"], "contact-info": {"person": ["Makuru"], "e-mail": ["Makuru+DN42@makuru.org"], "nic-hdl": ["MAKURU-DN42"], "mnt-by": ["MAKURU-MNT"], "source": ["DN42"], "pgp-fingerprint": "ssh-ed25519 AAAAC3NzaC1lZDI1NTE5AAAAIPRRdToCDUupkkwI+crB3fGDwdBIFkDsBHjOImn+qsjg openpgp:0xE8D3D833"}}, "routes": {"ipv4": [{"route": ["172.20.175.128/27"], "origin": ["AS4242423424"], "max-length": ["27"], "mnt-by": ["MAKURU-MNT"], "source": ["DN42"], "inetnum": {"cidr": ["172.20.175.128/27"], "netname": ["MAKURU-NETWORK"], "descr": ["Network of Makuru"], "country": ["DE"], "admin-c": ["MAKURU-DN42"], "tech-c": ["MAKURU-DN42"], "mnt-by": ["MAKURU-MNT"], "status": ["ASSIGNED"], "nserver": ["ns1.makuru.dn42", "ns2.makuru.dn42"], "source": ["DN42"]}, "visible": false}], "ipv6": [{"route6": ["fdc4:a95f:f73e::/48"], "origin": ["AS4242423424"], "max-length": ["48"], "mnt-by": ["MAKURU-MNT"], "source": ["DN42"], "inetnum": {"cidr": ["fdc4:a95f:f73e::/48"], "netname": ["MAKURU-NETWORK"], "descr": ["Network of MAKURU"], "country": ["DE"], "admin-c": ["MAKURU-DN42"], "tech-c": ["MAKURU-DN42"], "mnt-by": ["MAKURU-MNT"], "status": ["ASSIGNED"], "nserver": ["ns1.makuru.dn42", "ns2.makuru.dn42"], "source": ["DN42"]}, "visible": false}]}}