{"created": 1689853144, "asn": {"aut-num": ["AS4242420912"], "as-name": ["AS-KOBENET"], "admin-c": ["KOBE-DN42"], "tech-c": ["KOBE-DN42"], "mnt-by": ["KOBE-MNT"], "source": ["DN42"], "contact-info": {"person": ["Matthew Kobayashi"], "e-mail": ["matthew@kobayashi.au"], "nic-hdl": ["KOBE-DN42"], "mnt-by": ["KOBE-MNT"], "source": ["DN42"], "pgp-fingerprint": "ssh-ed25519 AAAAC3NzaC1lZDI1NTE5AAAAII5u9yJ0ssOXAnh/nJ7GDsjKuAVdka2joAe4oi9b3HPY"}}, "routes": {"ipv4": [{"route": ["172.21.94.32/27"], "origin": ["AS4242420912"], "mnt-by": ["KOBE-MNT"], "source": ["DN42"], "inetnum": {"cidr": ["172.21.94.32/27"], "netname": ["KOBE-NETWORK"], "descr": ["KobayashiNet"], "admin-c": ["KOBE-DN42"], "tech-c": ["KOBE-DN42"], "mnt-by": ["KOBE-MNT"], "status": ["ASSIGNED"], "source": ["DN42"]}, "visible": false}], "ipv6": [{"route6": ["fd0d:fcde:34b0::/48"], "origin": ["AS4242420912"], "max-length": ["48"], "mnt-by": ["KOBE-MNT"], "source": ["DN42"], "inetnum": {"cidr": ["fd0d:fcde:34b0::/48"], "netname": ["KOBE-NETWORK"], "descr": ["KobayashiNet"], "country": ["AU"], "admin-c": ["KOBE-DN42"], "tech-c": ["KOBE-DN42"], "mnt-by": ["KOBE-MNT"], "status": ["ASSIGNED"], "source": ["DN42"]}, "visible": false}]}}