{"created": 1694396417, "asn": {"aut-num": ["AS4242420842"], "as-name": ["NET-REWBYCRAFT-AS202562"], "admin-c": ["REWBYCRAFT-DN42"], "tech-c": ["REWBYCRAFT-DN42"], "mnt-by": ["REWBYSOFT-MNT"], "source": ["DN42"], "contact-info": {"person": ["Roelf Wichertjes"], "contact": ["contact@roelf.org"], "nic-hdl": ["REWBYCRAFT-DN42"], "mnt-by": ["REWBYSOFT-MNT"], "source": ["DN42"]}}, "routes": {"ipv4": [{"route": ["172.20.140.0/23"], "origin": ["AS4242420842"], "mnt-by": ["REWBYSOFT-MNT"], "source": ["DN42"], "inetnum": {"netname": ["APERTURE-NETWORKS-NET"], "descr": ["Used by rewbycraft throughout his primary global network. Expected to come online mid-march."], "country": ["NL"], "admin-c": ["REWBYCRAFT-DN42"], "tech-c": ["REWBYCRAFT-DN42"], "mnt-by": ["REWBYSOFT-MNT"], "status": ["ASSIGNED"], "cidr": ["172.20.140.0/23"], "source": ["DN42"]}, "visible": false}], "ipv6": [{"route6": ["fdca:852a:928d::/48"], "origin": ["AS4242420842"], "mnt-by": ["REWBYSOFT-MNT"], "source": ["DN42"], "inetnum": {"netname": ["NET-REWBYSOFT-001"], "remarks": ["This prefix will be decomissioned shortly."], "country": ["NL"], "admin-c": ["REWBYCRAFT-DN42"], "tech-c": ["REWBYCRAFT-DN42"], "mnt-by": ["REWBYSOFT-MNT"], "status": ["ASSIGNED"], "cidr": ["fdca:852a:928d::/48"], "source": ["DN42"]}, "visible": false}, {"route6": ["fd06:e881:1300::/44"], "origin": ["AS4242420842"], "mnt-by": ["REWBYSOFT-MNT"], "source": ["DN42"], "inetnum": {"netname": ["NET-REWBYSOFT-VMCLUSTER"], "nserver": ["ns1.aperture-laboratories.dn42"], "country": ["NL"], "admin-c": ["REWBYCRAFT-DN42"], "tech-c": ["REWBYCRAFT-DN42"], "mnt-by": ["REWBYSOFT-MNT"], "status": ["ASSIGNED"], "cidr": ["fd06:e881:1300::/44"], "source": ["DN42"]}, "visible": false}]}}