{"created": 1687784516, "asn": {"aut-num": ["AS4242422496"], "as-name": ["AS-WIGUST-DN42"], "admin-c": ["WIGUST-DN42"], "tech-c": ["WIGUST-DN42"], "mnt-by": ["WIGUST-MNT"], "source": ["DN42"], "contact-info": {"person": ["Oleg Pykhalov"], "e-mail": ["wigust@wugi.info"], "nic-hdl": ["WIGUST-DN42"], "mnt-by": ["WIGUST-MNT"], "source": ["DN42"], "pgp-fingerprint": "pgp-fingerprint 723871238EACEB6345485857167F8EA5001AFA9C"}}, "routes": {"ipv4": [{"route": ["172.22.144.96/27"], "origin": ["AS4242422496"], "mnt-by": ["WIGUST-MNT"], "source": ["DN42"], "inetnum": {"cidr": ["172.22.144.96/27"], "netname": ["WIGUST-NETWORK"], "admin-c": ["WIGUST-DN42"], "tech-c": ["WIGUST-DN42"], "mnt-by": ["WIGUST-MNT"], "status": ["ASSIGNED"], "source": ["DN42"]}, "visible": true}], "ipv6": []}}