{"created": 1688190083, "asn": {"aut-num": ["AS4242423008"], "as-name": ["AS-STATHIS"], "admin-c": ["STATHIS-DN42"], "tech-c": ["STATHIS-DN42"], "mnt-by": ["STATHIS-MNT"], "source": ["DN42"], "contact-info": {"person": ["Stathis"], "contact": ["stathis@stathis.ch"], "nic-hdl": ["STATHIS-DN42"], "mnt-by": ["STATHIS-MNT"], "source": ["DN42"], "pgp-fingerprint": "pgp-fingerprint 59C223CA709F238ECD5F3C7133E1315BEF56887F"}}, "routes": {"ipv4": [{"route": ["172.20.21.192/26"], "origin": ["AS4242423008"], "mnt-by": ["STATHIS-MNT"], "source": ["DN42"], "inetnum": {"cidr": ["172.20.21.192/26"], "netname": ["STATHIS-NETWORK"], "admin-c": ["STATHIS-DN42"], "tech-c": ["STATHIS-DN42"], "mnt-by": ["STATHIS-MNT"], "status": ["ASSIGNED"], "source": ["DN42"]}, "visible": false}], "ipv6": [{"route6": ["fd2a:8eb0:74bd::/48"], "origin": ["AS4242423008"], "mnt-by": ["STATHIS-MNT"], "source": ["DN42"], "inetnum": {"cidr": ["fd2a:8eb0:74bd::/48"], "netname": ["STATHIS-NETWORK"], "descr": ["STATHIS-NET"], "country": ["GR"], "admin-c": ["STATHIS-DN42"], "tech-c": ["STATHIS-DN42"], "mnt-by": ["STATHIS-MNT"], "status": ["ASSIGNED"], "source": ["DN42"]}, "visible": false}]}}