{"created": 1639431524, "asn": {"aut-num": ["AS4242420134"], "as-name": ["NOP-TEST"], "descr": ["nop test"], "admin-c": ["MC36-DN42"], "tech-c": ["MC36-DN42"], "mnt-by": ["NOP-MNT"], "source": ["DN42"], "contact-info": {"person": ["mc36"], "contact": ["irc:mc36 @ hackint.org"], "e-mail": ["mc36@freemail.hu"], "nic-hdl": ["MC36-DN42"], "mnt-by": ["NOP-MNT"], "source": ["DN42"]}}, "routes": {"ipv4": [{"route": ["172.23.199.96/28"], "descr": ["nop test"], "origin": ["AS4242420134"], "mnt-by": ["NOP-MNT"], "source": ["DN42"], "inetnum": {"netname": ["NOP-TEST4"], "descr": ["nop test"], "country": ["HU"], "admin-c": ["MC36-DN42"], "tech-c": ["MC36-DN42"], "mnt-by": ["NOP-MNT"], "nserver": ["ns.nop.dn42"], "status": ["ASSIGNED"], "cidr": ["172.23.199.96/28"], "source": ["DN42"]}, "visible": true}, {"route": ["172.23.43.64/27"], "descr": ["nop demo"], "origin": ["AS4242420134"], "mnt-by": ["NOP-MNT"], "source": ["DN42"], "inetnum": {"netname": ["NOP-DEMO4"], "descr": ["nop demo"], "country": ["HU"], "admin-c": ["MC36-DN42"], "tech-c": ["MC36-DN42"], "mnt-by": ["NOP-MNT"], "nserver": ["ns.nop.dn42"], "status": ["ALLOCATED"], "cidr": ["172.23.43.64/27"], "source": ["DN42"]}, "visible": true}], "ipv6": [{"route6": ["fd40:2343:64:fa52::/64"], "descr": ["nop test"], "origin": ["AS4242420134"], "mnt-by": ["NOP-MNT"], "source": ["DN42"], "inetnum": {"netname": ["NOP-DEMO6"], "descr": ["nop demo"], "country": ["HU"], "admin-c": ["MC36-DN42"], "tech-c": ["MC36-DN42"], "mnt-by": ["NOP-MNT"], "nserver": ["ns.nop.dn42"], "status": ["ASSIGNED"], "cidr": ["fd40:2343:64:fa52::/64"], "source": ["DN42"]}, "visible": true}, {"route6": ["fd40:bad:dead:babe::/64"], "descr": ["nop test"], "origin": ["AS4242420134"], "mnt-by": ["NOP-MNT"], "source": ["DN42"], "inetnum": {"netname": ["NOP-TEST6"], "descr": ["nop test"], "country": ["HU"], "admin-c": ["MC36-DN42"], "tech-c": ["MC36-DN42"], "mnt-by": ["NOP-MNT"], "nserver": ["ns.nop.dn42"], "status": ["ASSIGNED"], "cidr": ["fd40:bad:dead:babe::/64"], "source": ["DN42"]}, "visible": true}]}}