{"created": 1696518966, "asn": {"aut-num": ["AS4242421350"], "as-name": ["KIYOMI-AS"], "descr": ["Peer with me at leijiajie.ljj@qq.com"], "admin-c": ["KIYOMI-DN42"], "tech-c": ["KIYOMI-DN42"], "mnt-by": ["KIYOMI-MNT"], "source": ["DN42"], "contact-info": {"person": ["Kiyomi"], "e-mail": ["leijiajie.ljj@qq.com"], "contact": ["telegram:K1roto"], "nic-hdl": ["KIYOMI-DN42"], "mnt-by": ["KIYOMI-MNT"], "source": ["DN42"], "pgp-fingerprint": "ssh-ed25519 AAAAC3NzaC1lZDI1NTE5AAAAIFxVANr+Srl3UtSy/ArUEV/ZveLH0kSaOkGV0FGC4aby leijiajie.ljj@qq.com"}}, "routes": {"ipv4": [{"route": ["172.20.39.80/28"], "origin": ["AS4242421350"], "max-length": ["28"], "mnt-by": ["KIYOMI-MNT"], "source": ["DN42"], "inetnum": {"netname": ["KIYOMI-IPV4"], "remarks": ["Peer with me at leijiajie.ljj@qq.com"], "descr": ["Peer with me at leijiajie.ljj@qq.com"], "country": ["CN"], "admin-c": ["KIYOMI-DN42"], "tech-c": ["KIYOMI-DN42"], "mnt-by": ["KIYOMI-MNT"], "status": ["ASSIGNED"], "cidr": ["172.20.39.80/28"], "source": ["DN42"]}, "visible": false}], "ipv6": [{"route6": ["fd9e:ed80:8884::/48"], "descr": ["Peer with me at leijiajie.ljj@qq.com"], "origin": ["AS4242421350"], "max-length": ["48"], "mnt-by": ["KIYOMI-MNT"], "source": ["DN42"], "inetnum": {"netname": ["KIYOMI-IPV6"], "descr": ["Peer with me at leijiajie.ljj@qq.com"], "country": ["CN"], "admin-c": ["KIYOMI-DN42"], "tech-c": ["KIYOMI-DN42"], "mnt-by": ["KIYOMI-MNT"], "status": ["ASSIGNED"], "cidr": ["fd9e:ed80:8884::/48"], "source": ["DN42"]}, "visible": false}]}}