{"created": 1690133957, "asn": {"aut-num": ["AS4242420129"], "as-name": ["PIVIPI-NET"], "mnt-by": ["MINECON724-MNT"], "admin-c": ["MINECON724-DN42"], "tech-c": ["MINECON724-DN42"], "source": ["DN42"], "remarks": ["https://inferior.network"], "contact-info": {"person": ["Minecon724"], "nic-hdl": ["MINECON724-DN42"], "mnt-by": ["MINECON724-MNT"], "e-mail": ["me@inferior.network"], "contact": ["telegram:Minecon724", "session:0516b06413fa381d789d0ca2fdafc114672d8b958c4119b67cde67588df6515831", "discord:minecon724"], "source": ["DN42"], "pgp-fingerprint": "pgp-fingerprint A58EF6EDF650BD26BE77457672C6C65765CFA587"}}, "routes": {"ipv4": [{"route": ["172.20.183.88/29"], "origin": ["AS4242420129"], "max-length": ["29"], "mnt-by": ["MINECON724-MNT"], "source": ["DN42"], "inetnum": {"cidr": ["172.20.183.88/29"], "netname": ["PIVIPI-NET"], "nserver": ["ns1.pivipi.dn42", "ns2.pivipi.dn42"], "ds-rdata": ["62403 15 2 80a57e76a65ec0495265efbdb922d92356721b7ec61746053d7944fdaf0811e3"], "country": ["PL"], "admin-c": ["MINECON724-DN42"], "tech-c": ["MINECON724-DN42"], "mnt-by": ["MINECON724-MNT"], "status": ["ASSIGNED"], "source": ["DN42"]}, "visible": true}], "ipv6": [{"route6": ["fdfe:8d0:7450::/48"], "origin": ["AS4242420129"], "max-length": ["48"], "mnt-by": ["MINECON724-MNT"], "source": ["DN42"], "inetnum": {"cidr": ["fdfe:8d0:7450::/48"], "netname": ["PIVIPI-NET"], "nserver": ["ns1.pivipi.dn42", "ns2.pivipi.dn42"], "ds-rdata": ["64024 15 2 f4490800c5d6a8810d8f461397e38aae377f4b81a6b5f7d8b2a3c240fb602882"], "country": ["PL"], "admin-c": ["MINECON724-DN42"], "tech-c": ["MINECON724-DN42"], "mnt-by": ["MINECON724-MNT"], "status": ["ASSIGNED"], "source": ["DN42"]}, "visible": true}]}}