{"created": 1696194583, "asn": {"aut-num": ["AS4242423225"], "as-name": ["IRONFLAKE"], "descr": ["IRONFLAKE Network"], "admin-c": ["KEGERUNEKU-DN42"], "tech-c": ["KEGERUNEKU-DN42"], "mnt-by": ["IRONFLAKE-MNT"], "source": ["DN42"], "contact-info": {"person": ["KEGERUNEKU"], "e-mail": ["kegeruneku+dn42@ironflake.org"], "contact": ["irc:Kegeruneku@freenode", "twitter:Kegeruneku"], "pgp-fingerprint": "pgp-fingerprint 49999CCC3D9A6DB5AEBCCBE2D4AAA74BA5387C21", "nic-hdl": ["KEGERUNEKU-DN42"], "mnt-by": ["IRONFLAKE-MNT"], "source": ["DN42"]}}, "routes": {"ipv4": [{"route": ["172.22.149.32/28"], "origin": ["AS4242423225"], "mnt-by": ["IRONFLAKE-MNT"], "source": ["DN42"], "inetnum": {"cidr": ["172.22.149.32/28"], "netname": ["IRONFLAKE-NETWORK"], "admin-c": ["KEGERUNEKU-DN42"], "tech-c": ["KEGERUNEKU-DN42"], "mnt-by": ["IRONFLAKE-MNT"], "status": ["ASSIGNED"], "source": ["DN42"]}, "visible": false}], "ipv6": [{"route6": ["fd2e:56cf:1ec2::/48"], "origin": ["AS4242423225"], "mnt-by": ["IRONFLAKE-MNT"], "source": ["DN42"], "inetnum": {"cidr": ["fd2e:56cf:1ec2::/48"], "netname": ["IRONFLAKE-NETWORK"], "descr": ["Ironflake's Network"], "country": ["FR"], "admin-c": ["KEGERUNEKU-DN42"], "tech-c": ["KEGERUNEKU-DN42"], "mnt-by": ["IRONFLAKE-MNT"], "status": ["ASSIGNED"], "source": ["DN42"]}, "visible": false}]}}