{"created": 1687751386, "asn": {"aut-num": ["AS4242421994"], "as-name": ["AS-RLKT"], "descr": ["Ralukat.eu Networks"], "remarks": ["+--------------------------+", "| RALUKAT.eu TESTNET       |", "| VPN connection available |", "+--------------------------+"], "admin-c": ["RLKT-DN42"], "tech-c": ["RLKT-DN42"], "mnt-by": ["RLKT-MNT"], "source": ["DN42"], "contact-info": {"person": ["RLKTAdmin"], "contact": ["admin@ralukat.eu"], "nic-hdl": ["RLKT-DN42"], "mnt-by": ["RLKT-MNT"], "source": ["DN42"], "pgp-fingerprint": "pgp-fingerprint C4E88337005AF2E9F5AABB7CA3DFB9B48AA1B865"}}, "routes": {"ipv4": [{"route": ["172.21.89.32/27"], "origin": ["AS4242421994"], "mnt-by": ["RLKT-MNT"], "source": ["DN42"], "inetnum": {"netname": ["NET-RLKT"], "descr": ["RLKT assigned addresses"], "country": ["DE"], "admin-c": ["RLKT-DN42"], "tech-c": ["RLKT-DN42"], "mnt-by": ["RLKT-MNT"], "status": ["ASSIGNED"], "cidr": ["172.21.89.32/27"], "source": ["DN42"]}, "visible": false}], "ipv6": [{"route6": ["fdfd:6b61:7431::/48"], "descr": ["RLKT assigned addresses (ipv6)"], "origin": ["AS4242421994"], "mnt-by": ["RLKT-MNT"], "source": ["DN42"], "inetnum": {"cidr": ["fdfd:6b61:7431::/48"], "netname": ["NET6-RLKT"], "admin-c": ["RLKT-DN42"], "tech-c": ["RLKT-DN42"], "mnt-by": ["RLKT-MNT"], "status": ["ASSIGNED"], "source": ["DN42"]}, "visible": false}]}}