{"created": 1694830942, "asn": {"aut-num": ["AS4242421788"], "as-name": ["TSX AS"], "admin-c": ["TSX-DN42"], "tech-c": ["TSX-DN42"], "mnt-by": ["TSX-MNT"], "source": ["DN42"], "contact-info": {"person": ["Vyacheslav aka tsx"], "contact": ["tsx@tsx.su"], "pgp-fingerprint": "pgp-fingerprint E7A882227D36426757803250A5176A54558E94DA", "nic-hdl": ["TSX-DN42"], "mnt-by": ["TSX-MNT"], "source": ["DN42"]}}, "routes": {"ipv4": [{"route": ["172.20.184.160/28"], "origin": ["AS4242421788"], "mnt-by": ["TSX-MNT"], "source": ["DN42"], "inetnum": {"cidr": ["172.20.184.160/28"], "netname": ["TSX-HOME-NET"], "admin-c": ["TSX-DN42"], "tech-c": ["TSX-DN42"], "mnt-by": ["TSX-MNT"], "status": ["ASSIGNED"], "source": ["DN42"]}, "visible": false}], "ipv6": [{"route6": ["fdfe:b58d:7621::/48"], "origin": ["AS4242421788"], "mnt-by": ["TSX-MNT"], "source": ["DN42"], "inetnum": {"cidr": ["fdfe:b58d:7621::/48"], "netname": ["TSX-HOME-NET"], "admin-c": ["TSX-DN42"], "tech-c": ["TSX-DN42"], "mnt-by": ["TSX-MNT"], "status": ["ASSIGNED"], "source": ["DN42"]}, "visible": false}]}}