{"created": 1693106013, "asn": {"aut-num": ["AS4242423482"], "as-name": ["AS-ROZINT-DN42"], "org": ["ORG-ROZINT"], "admin-c": ["ROZINT-DN42"], "tech-c": ["ROZINT-DN42"], "mnt-by": ["ROZINT-MNT"], "source": ["DN42"], "contact-info": {"person": ["Rozint"], "e-mail": ["it@rozint.com"], "nic-hdl": ["ROZINT-DN42"], "mnt-by": ["ROZINT-MNT"], "source": ["DN42"], "pgp-fingerprint": "pgp-fingerprint 314A0E69A669D0F35F2F8E9B0CF0441D440F74CE"}}, "routes": {"ipv4": [{"route": ["172.22.162.192/27"], "origin": ["AS4242423482"], "max-length": ["27"], "mnt-by": ["ROZINT-MNT"], "source": ["DN42"], "inetnum": {"cidr": ["172.22.162.192/27"], "netname": ["ROZINT-NETWORK"], "country": ["US"], "org": ["ORG-ROZINT"], "admin-c": ["ROZINT-DN42"], "tech-c": ["ROZINT-DN42"], "mnt-by": ["ROZINT-MNT"], "status": ["ASSIGNED"], "source": ["DN42"]}, "visible": false}], "ipv6": [{"route6": ["fdde:7d4f:e027::/48"], "origin": ["AS4242423482"], "max-length": ["48"], "mnt-by": ["ROZINT-MNT"], "source": ["DN42"], "inetnum": {"cidr": ["fdde:7d4f:e027::/48"], "netname": ["ROZINT-NETWORK"], "descr": ["Network of Rozint"], "country": ["US"], "org": ["ORG-ROZINT"], "admin-c": ["ROZINT-DN42"], "tech-c": ["ROZINT-DN42"], "mnt-by": ["ROZINT-MNT"], "status": ["ASSIGNED"], "source": ["DN42"]}, "visible": false}]}}