{"created": 1691043351, "asn": {"aut-num": ["AS4242421258"], "as-name": ["AS-IDDQD-DN42"], "admin-c": ["IDDQD-DN42"], "tech-c": ["IDDQD-DN42"], "mnt-by": ["IDDQD-MNT"], "source": ["DN42"], "contact-info": {"person": ["Evgeni Dimitrov"], "contact": ["evgeni.dimitrov@gmail.com"], "nic-hdl": ["IDDQD-DN42"], "mnt-by": ["IDDQD-MNT"], "source": ["DN42"], "pgp-fingerprint": "ssh-ed25519 AAAAC3NzaC1lZDI1NTE5AAAAICoHxaA9I77zF+8TYsm4P7b5pQdAHbMY6iGZ8Q8Nauco"}}, "routes": {"ipv4": [{"route": ["172.23.57.32/27"], "descr": ["IDDQD IPv4 route"], "origin": ["AS4242421258"], "mnt-by": ["IDDQD-MNT"], "source": ["DN42"], "inetnum": {"cidr": ["172.23.57.32/27"], "netname": ["IDDQD-NETWORK"], "admin-c": ["IDDQD-DN42"], "tech-c": ["IDDQD-DN42"], "mnt-by": ["IDDQD-MNT"], "status": ["ASSIGNED"], "source": ["DN42"]}, "visible": false}], "ipv6": []}}