{"created": 1652093226, "asn": {"aut-num": ["AS4242422206"], "as-name": ["TECHANIT"], "admin-c": ["EST-DN42"], "tech-c": ["EST-DN42"], "mnt-by": ["EST-MNT"], "source": ["DN42"], "contact-info": {"person": ["Erik Stomp"], "e-mail": ["dn42@est-it.de"], "contact": ["twitter:techanit_de"], "phone": ["+4915788718659"], "nick": ["Techanit"], "address": ["48712 Gescher, Germany"], "pgp-fingerprint": "pgp-fingerprint 40A2B5F2D4374B3DBAC44AF8A6FC82F9D4DB130C", "nic-hdl": ["EST-DN42"], "mnt-by": ["EST-MNT"], "source": ["DN42"]}}, "routes": {"ipv4": [{"route": ["172.22.131.144/28"], "origin": ["AS4242422206"], "max-length": ["28"], "admin-c": ["EST-DN42"], "tech-c": ["EST-DN42"], "mnt-by": ["EST-MNT"], "source": ["DN42"], "inetnum": {"cidr": ["172.22.131.144/28"], "netname": ["TECHANIT-NETWORK4"], "country": ["DE"], "admin-c": ["EST-DN42"], "tech-c": ["EST-DN42"], "mnt-by": ["EST-MNT"], "status": ["ASSIGNED"], "source": ["DN42"]}, "visible": true}], "ipv6": [{"route6": ["fd9f:621d:e6b4::/48"], "origin": ["AS4242422206"], "max-length": ["48"], "admin-c": ["EST-DN42"], "tech-c": ["EST-DN42"], "mnt-by": ["EST-MNT"], "source": ["DN42"], "inetnum": {"cidr": ["fd9f:621d:e6b4::/48"], "netname": ["TECHANIT-NETWORK6"], "country": ["DE"], "admin-c": ["EST-DN42"], "tech-c": ["EST-DN42"], "mnt-by": ["EST-MNT"], "status": ["ASSIGNED"], "source": ["DN42"]}, "visible": true}]}}