{"created": 1694747725, "asn": {"aut-num": ["AS4242421091"], "as-name": ["AS for MOZZNET Network"], "admin-c": ["MOZZNET-DN42"], "tech-c": ["MOZZNET-DN42"], "mnt-by": ["MOZZNET-MNT"], "source": ["DN42"], "contact-info": {"person": ["Mozzarella"], "e-mail": ["mozzarella@captainwebservices.com"], "contact": ["discord:MozzarellaFlameDoggo#8302", "irc:Mozzarella"], "nic-hdl": ["MOZZNET-DN42"], "mnt-by": ["MOZZNET-MNT"], "source": ["DN42"], "pgp-fingerprint": "pgp-fingerprint a7711f2ae90264d6aaee30940a9605b47580ae20"}}, "routes": {"ipv4": [{"route": ["172.21.67.160/28"], "origin": ["AS4242421091"], "mnt-by": ["MOZZNET-MNT"], "source": ["DN42"], "inetnum": {"cidr": ["172.21.67.160/28"], "netname": ["MOZZNET-NETWORK"], "admin-c": ["MOZZNET-DN42"], "tech-c": ["MOZZNET-DN42"], "mnt-by": ["MOZZNET-MNT"], "status": ["ASSIGNED"], "nserver": ["helium.ns.mozzarella.dn42"], "source": ["DN42"]}, "visible": false}], "ipv6": [{"route6": ["fd12:f590:c38c::/48"], "origin": ["AS4242421091"], "max-length": ["48"], "mnt-by": ["MOZZNET-MNT"], "source": ["DN42"], "inetnum": {"cidr": ["fd12:f590:c38c::/48"], "netname": ["MOZZNET-NETWORK"], "descr": ["Network on MOZZNET"], "country": ["US"], "admin-c": ["MOZZNET-DN42"], "tech-c": ["MOZZNET-DN42"], "mnt-by": ["MOZZNET-MNT"], "status": ["ASSIGNED"], "nserver": ["helium.ns.mozzarella.dn42"], "source": ["DN42"]}, "visible": false}]}}