{"created": 1695728355, "asn": {"aut-num": ["AS4242422364"], "as-name": ["RDEV-AS"], "admin-c": ["STEPHRDEV-DN42"], "tech-c": ["STEPHRDEV-DN42"], "mnt-by": ["RDEV-MNT"], "source": ["DN42"], "contact-info": {"person": ["stephrdev"], "contact": ["hostmaster@rdev.info"], "nic-hdl": ["STEPHRDEV-DN42"], "mnt-by": ["RDEV-MNT"], "source": ["DN42"], "pgp-fingerprint": "pgp-fingerprint 6188519258BC886126683E5986F7F6D3B4E800FC"}}, "routes": {"ipv4": [], "ipv6": [{"route6": ["fd42:456:e567::/48"], "origin": ["AS4242422364"], "mnt-by": ["RDEV-MNT"], "source": ["DN42"], "inetnum": {"cidr": ["fd42:456:e567::/48"], "netname": ["RDEV-NETWORK"], "descr": ["rdev.info Network"], "country": ["DE"], "admin-c": ["STEPHRDEV-DN42"], "tech-c": ["STEPHRDEV-DN42"], "mnt-by": ["RDEV-MNT"], "status": ["ASSIGNED"], "source": ["DN42"]}, "visible": false}]}}