{"created": 1694216393, "asn": {"aut-num": ["AS4242422712"], "as-name": ["Yourdaddy.dk"], "admin-c": ["YOURDADDY-DN42"], "tech-c": ["YOURDADDY-DN42"], "source": ["DN42"], "mnt-by": ["YOURDADDY-MNT"], "contact-info": {"person": ["Thomas Scholz"], "contact": ["thomas@scholz.dk"], "nic-hdl": ["YOURDADDY-DN42"], "source": ["DN42"], "mnt-by": ["YOURDADDY-MNT"], "pgp-fingerprint": "pgp-fingerprint E6881B0A4867344B24F7AA85F2E7FE9A68FB6166"}}, "routes": {"ipv4": [], "ipv6": [{"route6": ["fdf5:b4f8:1e89::/48"], "origin": ["AS4242422712"], "mnt-by": ["YOURDADDY-MNT"], "source": ["DN42"], "inetnum": {"cidr": ["fdf5:b4f8:1e89::/48"], "netname": ["YOURDADDY-NET1"], "descr": ["yourdaddy.dk network 1"], "country": ["DK"], "admin-c": ["YOURDADDY-DN42"], "tech-c": ["YOURDADDY-DN42"], "mnt-by": ["YOURDADDY-MNT"], "source": ["DN42"], "status": ["ASSIGNED"]}, "visible": false}]}}