{"created": 1690877881, "asn": {"aut-num": ["AS4242420294"], "as-name": ["INKY-AS"], "descr": ["Inky Network"], "admin-c": ["INKY-DN42"], "tech-c": ["INKY-DN42"], "mnt-by": ["INKY-MNT"], "source": ["DN42"], "contact-info": {"person": ["INKY"], "e-mail": ["cuispeca@proton.me"], "nic-hdl": ["INKY-DN42"], "mnt-by": ["INKY-MNT"], "source": ["DN42"], "pgp-fingerprint": "pgp-fingerprint CA6D4F66F75AB8CB761FB25FDEBF11773068FC02"}}, "routes": {"ipv4": [{"route": ["172.21.117.64/26"], "descr": ["Inky Network"], "origin": ["AS4242420294"], "mnt-by": ["INKY-MNT"], "source": ["DN42"], "inetnum": {"netname": ["INKY-IPV4"], "descr": ["Inky Network"], "country": ["US"], "admin-c": ["INKY-DN42"], "tech-c": ["INKY-DN42"], "mnt-by": ["INKY-MNT"], "status": ["ASSIGNED"], "cidr": ["172.21.117.64/26"], "source": ["DN42"]}, "visible": false}], "ipv6": [{"route6": ["fd88:b679:21f8::/48"], "descr": ["Inky Network"], "origin": ["AS4242420294"], "mnt-by": ["INKY-MNT"], "source": ["DN42"], "inetnum": {"netname": ["INKY-IPV6"], "descr": ["Inky Network"], "country": ["US"], "admin-c": ["INKY-DN42"], "tech-c": ["INKY-DN42"], "mnt-by": ["INKY-MNT"], "status": ["ASSIGNED"], "cidr": ["fd88:b679:21f8::/48"], "source": ["DN42"]}, "visible": false}]}}