{"created": 1688102206, "asn": {"aut-num": ["AS4242423319"], "as-name": ["NTEREN-IX-AS"], "descr": ["NaiveTomcat Experimental eXchange"], "remarks": ["An experimental exchange", "To join contact tomdang@naivetomcat.cn", "Or https://t.me/naivetomcat"], "admin-c": ["TOMDANG-DN42"], "tech-c": ["TOMDANG-DN42"], "mnt-by": ["TOMDANG-MNT"], "source": ["DN42"], "contact-info": {"person": ["Tom Dang"], "contact": ["tomdang@naivetomcat.cn"], "nic-hdl": ["TOMDANG-DN42"], "mnt-by": ["TOMDANG-MNT"], "source": ["DN42"], "pgp-fingerprint": "pgp-fingerprint B5EB6EA969688B74853918EDEBA7269DA2D7E015"}}, "routes": {"ipv4": [], "ipv6": []}}