{"created": 1691424968, "asn": {"aut-num": ["AS4242421028"], "as-name": ["VPLINK-AS"], "descr": ["VPLINK's Main network, open to peering."], "admin-c": ["VPLINK-DN42"], "tech-c": ["VPLINK-DN42"], "mnt-by": ["VPLINK-MNT"], "source": ["DN42"], "contact-info": {"person": ["VPLINK"], "e-mail": ["31381881@qq.com"], "nic-hdl": ["VPLINK-DN42"], "mnt-by": ["VPLINK-MNT"], "source": ["DN42"], "pgp-fingerprint": "pgp-fingerprint F74F8DF14673922D78EA2377F66F06365F553C71"}}, "routes": {"ipv4": [{"route": ["172.22.252.128/27"], "descr": ["VPLINK's IP space"], "origin": ["AS4242421028"], "mnt-by": ["VPLINK-MNT"], "source": ["DN42"], "inetnum": {"netname": ["VPLINK-IPV4"], "descr": ["VPLINK's IP space"], "country": ["CN"], "admin-c": ["VPLINK-DN42"], "tech-c": ["VPLINK-DN42"], "mnt-by": ["VPLINK-MNT"], "status": ["ASSIGNED"], "cidr": ["172.22.252.128/27"], "source": ["DN42"]}, "visible": false}], "ipv6": [{"route6": ["fd08:7cc4:9598::/48"], "descr": ["VPLINK's IP space"], "origin": ["AS4242421028"], "mnt-by": ["VPLINK-MNT"], "source": ["DN42"], "inetnum": {"netname": ["VPLINK-IPV6"], "descr": ["VPLINK's IP space"], "country": ["CN"], "admin-c": ["VPLINK-DN42"], "tech-c": ["VPLINK-DN42"], "mnt-by": ["VPLINK-MNT"], "status": ["ASSIGNED"], "cidr": ["fd08:7cc4:9598::/48"], "source": ["DN42"]}, "visible": false}]}}