{"created": 1693170645, "asn": {"aut-num": ["AS4242423929"], "as-name": ["AS for v0ttis Network"], "admin-c": ["V0TTI-DN42"], "tech-c": ["V0TTI-DN42"], "mnt-by": ["V0TTI-MNT"], "source": ["DN42"], "contact-info": {"person": ["v0tti"], "contact": ["dn42@v0tti.com"], "nic-hdl": ["V0TTI-DN42"], "mnt-by": ["V0TTI-MNT"], "source": ["DN42"], "pgp-fingerprint": "pgp-fingerprint 6B5EA3CC537BFF050E88CBC31A0F27DF3B7D7869"}}, "routes": {"ipv4": [], "ipv6": [{"route6": ["fd23:1d71:dd17::/48"], "origin": ["AS4242423929"], "max-length": ["48"], "mnt-by": ["V0TTI-MNT"], "source": ["DN42"], "inetnum": {"cidr": ["fd23:1d71:dd17::/48"], "netname": ["V0TTI-NETWORK"], "descr": ["v0ttis Network"], "country": ["DE"], "admin-c": ["V0TTI-DN42"], "tech-c": ["V0TTI-DN42"], "mnt-by": ["V0TTI-MNT"], "status": ["ASSIGNED"], "nserver": ["ns1.v0tti.dn42"], "source": ["DN42"]}, "visible": true}]}}