{"created": 1688966062, "asn": {"aut-num": ["AS62396"], "as-name": ["Marcels AS"], "admin-c": ["MFK-DN42"], "tech-c": ["MFK-DN42"], "mnt-by": ["MFK-MNT"], "source": ["RIPE"], "contact-info": {"person": ["Marcel Krueger"], "e-mail": ["dn42@2krueger.de"], "pgp-fingerprint": "ssh-ed25519 AAAAC3NzaC1lZDI1NTE5AAAAIGbRsoPoGmEtaXQ064oEtfK1MJLZat15XZcxONw41MgV", "nic-hdl": ["MFK-DN42"], "mnt-by": ["MFK-MNT"], "source": ["DN42"]}}, "routes": {"ipv4": [{"route": ["172.23.4.32/27"], "origin": ["AS62396"], "max-length": ["27"], "mnt-by": ["MFK-MNT"], "source": ["DN42"], "inetnum": {"cidr": ["172.23.4.32/27"], "netname": ["MFK4-NET"], "country": ["DE"], "admin-c": ["MFK-DN42"], "tech-c": ["MFK-DN42"], "mnt-by": ["MFK-MNT"], "status": ["ASSIGNED"], "source": ["DN42"]}, "visible": true}], "ipv6": [{"route6": ["fd97:36:c802::/48"], "origin": ["AS62396"], "max-length": ["48"], "mnt-by": ["MFK-MNT"], "source": ["DN42"], "inetnum": {"cidr": ["fd97:36:c802::/48"], "netname": ["MFK-NET"], "country": ["DE"], "admin-c": ["MFK-DN42"], "tech-c": ["MFK-DN42"], "mnt-by": ["MFK-MNT"], "status": ["ASSIGNED"], "source": ["DN42"]}, "visible": true}]}}