{"created": 1692882930, "asn": {"aut-num": ["AS64600"], "as-name": ["HEXA-AS"], "admin-c": ["HEXA-DN42"], "tech-c": ["HEXA-DN42"], "mnt-by": ["HEXA-MNT"], "source": ["DN42"], "contact-info": {"person": ["hexa"], "contact": ["martin@darmstadt.freifunk.net"], "nic-hdl": ["HEXA-DN42"], "mnt-by": ["HEXA-MNT"], "source": ["DN42"], "pgp-fingerprint": "pgp-fingerprint F7D67CFBF2CA32F1641A03DB0D9F700847860BC5"}}, "routes": {"ipv4": [{"route": ["172.20.66.64/28"], "descr": ["hackint"], "remarks": ["https://www.hackint.org"], "origin": ["AS64600", "AS4242420101"], "mnt-by": ["HEXA-MNT"], "source": ["DN42"], "inetnum": {"cidr": ["172.20.66.64/28"], "remarks": ["__               __", "/ /_  ____ ______/ /__", "/ __ \\/ __ `/ ___/ //_/", "/ / / / /_/ / /__/ ,<            __", "/_/ /_/\\__,_/\\___/_/|_|  (*)___  / /_", "/ / __ \\/ __/", "irc.hackint.org   / / / / / /_", "irc.hackint.eu  /_/_/ /_/\\__/", "irc.hackint.dn42"], "netname": ["HACKINT-DN42"], "descr": ["hackint dn42"], "country": ["DE"], "admin-c": ["HEXA-DN42"], "tech-c": ["HEXA-DN42"], "mnt-by": ["HEXA-MNT"], "nserver": ["ns1.cccda.dn42"], "status": ["ASSIGNED"], "source": ["DN42"]}, "visible": true}, {"route": ["172.23.42.0/24"], "origin": ["AS64600", "AS4242420101"], "pingable": ["172.23.42.3"], "mnt-by": ["HEXA-MNT"], "source": ["DN42"], "inetnum": {"cidr": ["172.23.42.0/24"], "descr": ["hexa"], "netname": ["HEXA-20171114"], "nserver": ["ns2.lossy-network.dn42"], "admin-c": ["HEXA-DN42"], "tech-c": ["HEXA-DN42"], "mnt-by": ["HEXA-MNT"], "status": ["ALLOCATED"], "source": ["DN42"]}, "visible": true}], "ipv6": [{"route6": ["fd01:470:7d4c::/48"], "origin": ["AS64600"], "mnt-by": ["HEXA-MNT"], "source": ["DN42"], "inetnum": {}, "visible": false}, {"route6": ["fd42:d42:d42:6667::/64"], "descr": ["hackint"], "remarks": ["https://www.hackint.org"], "origin": ["AS64600", "AS4242420101"], "mnt-by": ["HEXA-MNT"], "source": ["DN42"], "inetnum": {"cidr": ["fd42:d42:d42:6667::/64"], "remarks": ["__               __", "/ /_  ____ ______/ /__", "/ __ \\/ __ `/ ___/ //_/", "/ / / / /_/ / /__/ ,<            __", "/_/ /_/\\__,_/\\___/_/|_|  (*)___  / /_", "/ / __ \\/ __/", "irc.hackint.org   / / / / / /_", "irc.hackint.eu  /_/_/ /_/\\__/", "irc.hackint.dn42", ""], "netname": ["HACKINT-DN42"], "country": ["DE"], "admin-c": ["HEXA-DN42"], "tech-c": ["HEXA-DN42"], "mnt-by": ["HEXA-MNT"], "nserver": ["ns1.cccda.dn42"], "status": ["ASSIGNED"], "source": ["DN42"]}, "visible": true}, {"route6": ["fd42:23:42::/48"], "origin": ["AS64600", "AS4242420101"], "pingable": ["fd42:23:42:b300::1"], "mnt-by": ["HEXA-MNT"], "source": ["DN42"], "inetnum": {"cidr": ["fd42:23:42::/48"], "netname": ["NET-HEXA"], "nserver": ["ns1.lossy-network.dn42", "ns2.lossy-network.dn42"], "country": ["DE"], "admin-c": ["HEXA-DN42"], "tech-c": ["HEXA-DN42"], "mnt-by": ["HEXA-MNT"], "status": ["ASSIGNED"], "source": ["DN42"]}, "visible": true}]}}